{"level":"info","message":"There's a POST on /network","timestamp":"2018-02-06T20:28:12.305Z"}
{"level":"info","message":"There's a GET on /network","timestamp":"2018-02-06T20:28:12.378Z"}
{"level":"info","message":"responding with a 404","timestamp":"2018-02-06T20:28:12.382Z"}
{"level":"info","message":"There's a POST on /network","timestamp":"2018-02-06T20:28:53.715Z"}
{"level":"info","message":"There's a GET on /network","timestamp":"2018-02-06T20:28:53.770Z"}
{"level":"info","message":"responding with a 404","timestamp":"2018-02-06T20:28:53.774Z"}
{"level":"info","message":"There's a POST on /network","timestamp":"2018-02-06T20:29:47.702Z"}
{"level":"info","message":"There's a GET on /network","timestamp":"2018-02-06T20:29:47.761Z"}
{"level":"info","message":"responding with a 404","timestamp":"2018-02-06T20:29:47.766Z"}
{"level":"info","message":"There's a POST on /network","timestamp":"2018-02-06T20:30:14.143Z"}
{"level":"info","message":"There's a GET on /network","timestamp":"2018-02-06T20:30:14.199Z"}
{"level":"info","message":"responding with a 404","timestamp":"2018-02-06T20:30:14.206Z"}
{"level":"info","message":"There's a POST on /network","timestamp":"2018-02-06T20:43:07.189Z"}
{"level":"info","message":"There's a GET on /network","timestamp":"2018-02-06T20:43:07.253Z"}
{"level":"info","message":"responding with a 404","timestamp":"2018-02-06T20:43:07.256Z"}
{"level":"info","message":"There's a POST on /network","timestamp":"2018-02-06T20:51:10.033Z"}
{"level":"info","message":"There's a GET on /network","timestamp":"2018-02-06T20:51:10.093Z"}
{"level":"info","message":"responding with a 404","timestamp":"2018-02-06T20:51:10.097Z"}
